<?xml version="1.0" encoding="UTF-8"?>
<gml:Dictionary xmlns:gml="http://www.opengis.net/gml/3.2" xmlns:xsi="http://www.w3.org/2001/XMLSchema-instance" xsi:schemaLocation="http://www.opengis.net/gml/3.2 http://schemas.opengis.net/gml/3.2.1/gml.xsd" gml:id="kodelister.5074">
	<gml:description>Ulykkens alvorlighetsgrad.</gml:description>
	<gml:identifier codeSpace="https://github.com/tonoarmas/kodelister/blob/main/Alvorlighetsgrad_5074.xml">Alvorlighetsgrad_5074</gml:identifier>
	<gml:dictionaryEntry>
		<gml:Definition gml:id="6427">
			<gml:description>Dødsulykke</gml:description>
			<gml:identifier codeSpace="https://github.com/tonoarmas/kodelister/blob/main/Alvorlighetsgrad_5074.xml">6427</gml:identifier>
			<gml:name>Dødsulykke</gml:name>
		</gml:Definition>
	</gml:dictionaryEntry>
</gml:Dictionary>
