<?xml version="1.0" encoding="UTF-8"?>
<gml:Dictionary xmlns:gml="http://www.opengis.net/gml/3.2" xmlns:xsi="http://www.w3.org/2001/XMLSchema-instance" xsi:schemaLocation="http://www.opengis.net/gml/3.2 http://schemas.opengis.net/gml/3.2.1/gml.xsd" gml:id="kodelister.2250">
	<gml:description>Angir kvalitet på måling</gml:description>
	<gml:identifier codeSpace="https://github.com/tonoarmas/kodelister/blob/main/Kvalitet_2250.xml">Kvalitet_2250</gml:identifier>
	<gml:dictionaryEntry>
		<gml:Definition gml:id="4622">
			<gml:description></gml:description>
			<gml:identifier codeSpace="https://github.com/tonoarmas/kodelister/blob/main/Kvalitet_2250.xml">4622</gml:identifier>
			<gml:name>Skjønn</gml:name>
		</gml:Definition>
		<gml:Definition gml:id="4623">
			<gml:description></gml:description>
			<gml:identifier codeSpace="https://github.com/tonoarmas/kodelister/blob/main/Kvalitet_2250.xml">4623</gml:identifier>
			<gml:name>Målt</gml:name>
		</gml:Definition>
	</gml:dictionaryEntry>
</gml:Dictionary>
