<?xml version="1.0" encoding="UTF-8"?>
<gml:Dictionary xmlns:gml="http://www.opengis.net/gml/3.2" xmlns:xsi="http://www.w3.org/2001/XMLSchema-instance" xsi:schemaLocation="http://www.opengis.net/gml/3.2 http://schemas.opengis.net/gml/3.2.1/gml.xsd" gml:id="kodelister.10783">
	<gml:description>Angir skiltnumer på variabelt skilt i ordinær visningsmodus, dvs den visningen som er mest utbredt når skiltet ikke er avslått/blankt.</gml:description>
	<gml:identifier codeSpace="https://github.com/tonoarmas/kodelister/blob/main/SkiltnummerOrdinærVi_10783.xml">SkiltnummerOrdinærVi_10783</gml:identifier>
	<gml:dictionaryEntry>
		<gml:Definition gml:id="21323">
			<gml:description>Farlig sving, til høyre</gml:description>
			<gml:identifier codeSpace="https://github.com/tonoarmas/kodelister/blob/main/SkiltnummerOrdinærVi_10783.xml">21323</gml:identifier>
			<gml:name>100.1 - Farlig sving, til høyre</gml:name>
		</gml:Definition>
		<gml:Definition gml:id="21324">
			<gml:description>Farlig sving, til venstre</gml:description>
			<gml:identifier codeSpace="https://github.com/tonoarmas/kodelister/blob/main/SkiltnummerOrdinærVi_10783.xml">21324</gml:identifier>
			<gml:name>100.2 - Farlig sving, til venstre</gml:name>
		</gml:Definition>
		<gml:Definition gml:id="21325">
			<gml:description>Farlige svinger, den første til høyre</gml:description>
			<gml:identifier codeSpace="https://github.com/tonoarmas/kodelister/blob/main/SkiltnummerOrdinærVi_10783.xml">21325</gml:identifier>
			<gml:name>102.1 - Farlige svinger, den første til høyre</gml:name>
		</gml:Definition>
		<gml:Definition gml:id="21326">
			<gml:description>Farlige svinger, den første til venstre</gml:description>
			<gml:identifier codeSpace="https://github.com/tonoarmas/kodelister/blob/main/SkiltnummerOrdinærVi_10783.xml">21326</gml:identifier>
			<gml:name>102.2 - Farlige svinger, den første til venstre</gml:name>
		</gml:Definition>
		<gml:Definition gml:id="21327">
			<gml:description>Smalere veg, Innsnevring på begge sider</gml:description>
			<gml:identifier codeSpace="https://github.com/tonoarmas/kodelister/blob/main/SkiltnummerOrdinærVi_10783.xml">21327</gml:identifier>
			<gml:name>106.1 - Smalere veg, Innsnevring på begge sider</gml:name>
		</gml:Definition>
		<gml:Definition gml:id="21328">
			<gml:description>Smalere veg, Innsnevring på høyre side</gml:description>
			<gml:identifier codeSpace="https://github.com/tonoarmas/kodelister/blob/main/SkiltnummerOrdinærVi_10783.xml">21328</gml:identifier>
			<gml:name>106.2 - Smalere veg, Innsnevring på høyre side</gml:name>
		</gml:Definition>
		<gml:Definition gml:id="21329">
			<gml:description>Smalere veg, Innsnevring på venstre side</gml:description>
			<gml:identifier codeSpace="https://github.com/tonoarmas/kodelister/blob/main/SkiltnummerOrdinærVi_10783.xml">21329</gml:identifier>
			<gml:name>106.3 - Smalere veg, Innsnevring på venstre side</gml:name>
		</gml:Definition>
		<gml:Definition gml:id="19072">
			<gml:description>Vegarbeid</gml:description>
			<gml:identifier codeSpace="https://github.com/tonoarmas/kodelister/blob/main/SkiltnummerOrdinærVi_10783.xml">19072</gml:identifier>
			<gml:name>110 - Vegarbeid</gml:name>
		</gml:Definition>
		<gml:Definition gml:id="21331">
			<gml:description>Steinsprut</gml:description>
			<gml:identifier codeSpace="https://github.com/tonoarmas/kodelister/blob/main/SkiltnummerOrdinærVi_10783.xml">21331</gml:identifier>
			<gml:name>112 - Steinsprut</gml:name>
		</gml:Definition>
		<gml:Definition gml:id="21332">
			<gml:description>Glatt kjørebane</gml:description>
			<gml:identifier codeSpace="https://github.com/tonoarmas/kodelister/blob/main/SkiltnummerOrdinærVi_10783.xml">21332</gml:identifier>
			<gml:name>116 - Glatt kjørebane</gml:name>
		</gml:Definition>
		<gml:Definition gml:id="17932">
			<gml:description>Møtende trafikk</gml:description>
			<gml:identifier codeSpace="https://github.com/tonoarmas/kodelister/blob/main/SkiltnummerOrdinærVi_10783.xml">17932</gml:identifier>
			<gml:name>148 - Møtende trafikk</gml:name>
		</gml:Definition>
		<gml:Definition gml:id="17486">
			<gml:description>Kø</gml:description>
			<gml:identifier codeSpace="https://github.com/tonoarmas/kodelister/blob/main/SkiltnummerOrdinærVi_10783.xml">17486</gml:identifier>
			<gml:name>149 - Kø</gml:name>
		</gml:Definition>
		<gml:Definition gml:id="17477">
			<gml:description>Sidevind</gml:description>
			<gml:identifier codeSpace="https://github.com/tonoarmas/kodelister/blob/main/SkiltnummerOrdinærVi_10783.xml">17477</gml:identifier>
			<gml:name>152 - Sidevind</gml:name>
		</gml:Definition>
		<gml:Definition gml:id="17512">
			<gml:description>Trafikkulykke</gml:description>
			<gml:identifier codeSpace="https://github.com/tonoarmas/kodelister/blob/main/SkiltnummerOrdinærVi_10783.xml">17512</gml:identifier>
			<gml:name>153 - Trafikkulykke</gml:name>
		</gml:Definition>
		<gml:Definition gml:id="21330">
			<gml:description>Innkjøring forbudt</gml:description>
			<gml:identifier codeSpace="https://github.com/tonoarmas/kodelister/blob/main/SkiltnummerOrdinærVi_10783.xml">21330</gml:identifier>
			<gml:name>302 - Innkjøring forbudt</gml:name>
		</gml:Definition>
		<gml:Definition gml:id="17478">
			<gml:description>Forbudt for lastebil og trekkbil</gml:description>
			<gml:identifier codeSpace="https://github.com/tonoarmas/kodelister/blob/main/SkiltnummerOrdinærVi_10783.xml">17478</gml:identifier>
			<gml:name>306.5 - Forbudt for lastebil og trekkbil</gml:name>
		</gml:Definition>
		<gml:Definition gml:id="17495">
			<gml:description>Forbudt for motorvogn med flere enn to hjul og med tillatt totalvekt høyere enn angitt</gml:description>
			<gml:identifier codeSpace="https://github.com/tonoarmas/kodelister/blob/main/SkiltnummerOrdinærVi_10783.xml">17495</gml:identifier>
			<gml:name>310 - Forbudt for motorvogn med flere enn to hjul og med tillatt totalvekt høyere enn angitt</gml:name>
		</gml:Definition>
		<gml:Definition gml:id="17493">
			<gml:description>Forbikjøringsforbud for lastebil</gml:description>
			<gml:identifier codeSpace="https://github.com/tonoarmas/kodelister/blob/main/SkiltnummerOrdinærVi_10783.xml">17493</gml:identifier>
			<gml:name>335 - Forbikjøringsforbud for lastebil</gml:name>
		</gml:Definition>
		<gml:Definition gml:id="17494">
			<gml:description>Slutt på forbikjøringsforbud for lastebil</gml:description>
			<gml:identifier codeSpace="https://github.com/tonoarmas/kodelister/blob/main/SkiltnummerOrdinærVi_10783.xml">17494</gml:identifier>
			<gml:name>337 - Slutt på forbikjøringsforbud for lastebil</gml:name>
		</gml:Definition>
		<gml:Definition gml:id="17521">
			<gml:description>Fartsgrense 20 km/t</gml:description>
			<gml:identifier codeSpace="https://github.com/tonoarmas/kodelister/blob/main/SkiltnummerOrdinærVi_10783.xml">17521</gml:identifier>
			<gml:name>362.20 - Fartsgrense 20 km/t</gml:name>
		</gml:Definition>
		<gml:Definition gml:id="17513">
			<gml:description>Fartsgrense 30 km/t</gml:description>
			<gml:identifier codeSpace="https://github.com/tonoarmas/kodelister/blob/main/SkiltnummerOrdinærVi_10783.xml">17513</gml:identifier>
			<gml:name>362.30 - Fartsgrense 30 km/t</gml:name>
		</gml:Definition>
		<gml:Definition gml:id="17514">
			<gml:description>Fartsgrense 40 km/t</gml:description>
			<gml:identifier codeSpace="https://github.com/tonoarmas/kodelister/blob/main/SkiltnummerOrdinærVi_10783.xml">17514</gml:identifier>
			<gml:name>362.40 - Fartsgrense 40 km/t</gml:name>
		</gml:Definition>
		<gml:Definition gml:id="17515">
			<gml:description>Fartsgrense 50 km/t</gml:description>
			<gml:identifier codeSpace="https://github.com/tonoarmas/kodelister/blob/main/SkiltnummerOrdinærVi_10783.xml">17515</gml:identifier>
			<gml:name>362.50 - Fartsgrense 50 km/t</gml:name>
		</gml:Definition>
		<gml:Definition gml:id="17516">
			<gml:description>Fartsgrense 60 km/t</gml:description>
			<gml:identifier codeSpace="https://github.com/tonoarmas/kodelister/blob/main/SkiltnummerOrdinærVi_10783.xml">17516</gml:identifier>
			<gml:name>362.60 - Fartsgrense 60 km/t</gml:name>
		</gml:Definition>
		<gml:Definition gml:id="17517">
			<gml:description>Fartsgrense 70 km/t</gml:description>
			<gml:identifier codeSpace="https://github.com/tonoarmas/kodelister/blob/main/SkiltnummerOrdinærVi_10783.xml">17517</gml:identifier>
			<gml:name>362.70 - Fartsgrense 70 km/t</gml:name>
		</gml:Definition>
		<gml:Definition gml:id="17518">
			<gml:description>Fartsgrense 80 km/t</gml:description>
			<gml:identifier codeSpace="https://github.com/tonoarmas/kodelister/blob/main/SkiltnummerOrdinærVi_10783.xml">17518</gml:identifier>
			<gml:name>362.80 - Fartsgrense 80 km/t</gml:name>
		</gml:Definition>
		<gml:Definition gml:id="17519">
			<gml:description>Fartsgrense 90 km/t</gml:description>
			<gml:identifier codeSpace="https://github.com/tonoarmas/kodelister/blob/main/SkiltnummerOrdinærVi_10783.xml">17519</gml:identifier>
			<gml:name>362.90 - Fartsgrense 90 km/t</gml:name>
		</gml:Definition>
		<gml:Definition gml:id="17520">
			<gml:description>Fartsgrense 100 km/t</gml:description>
			<gml:identifier codeSpace="https://github.com/tonoarmas/kodelister/blob/main/SkiltnummerOrdinærVi_10783.xml">17520</gml:identifier>
			<gml:name>362.100 - Fartsgrense 100 km/t</gml:name>
		</gml:Definition>
		<gml:Definition gml:id="17522">
			<gml:description>Fartsgrense 110 km/t</gml:description>
			<gml:identifier codeSpace="https://github.com/tonoarmas/kodelister/blob/main/SkiltnummerOrdinærVi_10783.xml">17522</gml:identifier>
			<gml:name>362.110 - Fartsgrense 110 km/t</gml:name>
		</gml:Definition>
		<gml:Definition gml:id="21086">
			<gml:description>Slutt på særskilt fartsgrense 30 km/t</gml:description>
			<gml:identifier codeSpace="https://github.com/tonoarmas/kodelister/blob/main/SkiltnummerOrdinærVi_10783.xml">21086</gml:identifier>
			<gml:name>364.30 - Slutt på særskilt fartsgrense 30 km/t</gml:name>
		</gml:Definition>
		<gml:Definition gml:id="21087">
			<gml:description>Slutt på særskilt fartsgrense 40 km/t</gml:description>
			<gml:identifier codeSpace="https://github.com/tonoarmas/kodelister/blob/main/SkiltnummerOrdinærVi_10783.xml">21087</gml:identifier>
			<gml:name>364.40 - Slutt på særskilt fartsgrense 40 km/t</gml:name>
		</gml:Definition>
		<gml:Definition gml:id="21088">
			<gml:description>Slutt på særskilt fartsgrense 50 km/t</gml:description>
			<gml:identifier codeSpace="https://github.com/tonoarmas/kodelister/blob/main/SkiltnummerOrdinærVi_10783.xml">21088</gml:identifier>
			<gml:name>364.50 - Slutt på særskilt fartsgrense 50 km/t</gml:name>
		</gml:Definition>
		<gml:Definition gml:id="21089">
			<gml:description>Slutt på særskilt fartsgrense 60 km/t</gml:description>
			<gml:identifier codeSpace="https://github.com/tonoarmas/kodelister/blob/main/SkiltnummerOrdinærVi_10783.xml">21089</gml:identifier>
			<gml:name>364.60 - Slutt på særskilt fartsgrense 60 km/t</gml:name>
		</gml:Definition>
		<gml:Definition gml:id="21090">
			<gml:description>Slutt på særskilt fartsgrense 70 km/t</gml:description>
			<gml:identifier codeSpace="https://github.com/tonoarmas/kodelister/blob/main/SkiltnummerOrdinærVi_10783.xml">21090</gml:identifier>
			<gml:name>364.70 - Slutt på særskilt fartsgrense 70 km/t</gml:name>
		</gml:Definition>
		<gml:Definition gml:id="21109">
			<gml:description>Sammenfletting til 1 felt, motgående trafikk adskilt</gml:description>
			<gml:identifier codeSpace="https://github.com/tonoarmas/kodelister/blob/main/SkiltnummerOrdinærVi_10783.xml">21109</gml:identifier>
			<gml:name>530.01 - Sammenfletting til 1 felt, motgående trafikk adskilt</gml:name>
		</gml:Definition>
		<gml:Definition gml:id="21110">
			<gml:description>Sammenfeltting til 1 felt, motgående trafikk på samme kjørebane</gml:description>
			<gml:identifier codeSpace="https://github.com/tonoarmas/kodelister/blob/main/SkiltnummerOrdinærVi_10783.xml">21110</gml:identifier>
			<gml:name>530.11 - Sammenfeltting til 1 felt, motgående trafikk på samme kjørebane</gml:name>
		</gml:Definition>
		<gml:Definition gml:id="21111">
			<gml:description>Felt for fartsøking, gjennomgående veg, motgående trafikk atskilt, 1 gjennomgående felt i fartsretning</gml:description>
			<gml:identifier codeSpace="https://github.com/tonoarmas/kodelister/blob/main/SkiltnummerOrdinærVi_10783.xml">21111</gml:identifier>
			<gml:name>531.101 - Felt for fartsøkning, gjg. veg, motg. trafikk atskilt, 1 gjg. felt i fartsretn.</gml:name>
		</gml:Definition>
		<gml:Definition gml:id="21112">
			<gml:description>Felt for fartsøkning, gjennomg. veg, motgående trafikk adskilt, 2 gjennomgående felt i fartsretning</gml:description>
			<gml:identifier codeSpace="https://github.com/tonoarmas/kodelister/blob/main/SkiltnummerOrdinærVi_10783.xml">21112</gml:identifier>
			<gml:name>531.102 - Felt for fartsøkning, gjg. veg, motg. trafikk atskilt, 2 gjg. felt i fartsretn.</gml:name>
		</gml:Definition>
		<gml:Definition gml:id="21113">
			<gml:description>Felt for fartsøkning, gjennomg. veg, motgående trafikk adskilt, 3 gjennomgående felt i fartsretning</gml:description>
			<gml:identifier codeSpace="https://github.com/tonoarmas/kodelister/blob/main/SkiltnummerOrdinærVi_10783.xml">21113</gml:identifier>
			<gml:name>531.103 - Felt for fartsøkning, gjg. veg, motg. trafikk atskilt, 3 gjg. felt i fartsretn.</gml:name>
		</gml:Definition>
		<gml:Definition gml:id="21114">
			<gml:description>Felt for fartsøkning, gjennomg. veg, motgående trafikk adskilt, 4 gjennomgående felt i fartsretning</gml:description>
			<gml:identifier codeSpace="https://github.com/tonoarmas/kodelister/blob/main/SkiltnummerOrdinærVi_10783.xml">21114</gml:identifier>
			<gml:name>531.104 - Felt for fartsøkning, gjg. veg, motg. trafikk atskilt, 4 gjg. felt i fartsretn.</gml:name>
		</gml:Definition>
		<gml:Definition gml:id="21115">
			<gml:description>Felt for fartsøkning, gjennomg. veg, motgående trafikk adskilt, 5 gjennomgående felt i fartsretning</gml:description>
			<gml:identifier codeSpace="https://github.com/tonoarmas/kodelister/blob/main/SkiltnummerOrdinærVi_10783.xml">21115</gml:identifier>
			<gml:name>531.105 - Felt for fartsøkning, gjg. veg, motg. trafikk atskilt, 5 gjg. felt i fartsretning</gml:name>
		</gml:Definition>
		<gml:Definition gml:id="21116">
			<gml:description>Felt for fartsøkning, gjennomg. veg, motgående trafikk adskilt, 6 gjennomgående felt i fartsretning</gml:description>
			<gml:identifier codeSpace="https://github.com/tonoarmas/kodelister/blob/main/SkiltnummerOrdinærVi_10783.xml">21116</gml:identifier>
			<gml:name>531.106 - Felt for fartsøkning, gjg. veg, motg. trafikk atskilt, 6 gjg. felt i fartsretning</gml:name>
		</gml:Definition>
		<gml:Definition gml:id="21117">
			<gml:description>Felt for fartsøkning, gjennomg. veg, 1 felt mot, 1 gjennomgående felt i fartsretning</gml:description>
			<gml:identifier codeSpace="https://github.com/tonoarmas/kodelister/blob/main/SkiltnummerOrdinærVi_10783.xml">21117</gml:identifier>
			<gml:name>531.111 - Felt for fartsøkning, gjennomg. veg, 1 felt mot, 1 gjennomgående felt i fartsretning</gml:name>
		</gml:Definition>
		<gml:Definition gml:id="21118">
			<gml:description>Felt for fartsøkning, gjennomg. veg, 1 felt mot, 2 gjennomgående felt i fartsretning</gml:description>
			<gml:identifier codeSpace="https://github.com/tonoarmas/kodelister/blob/main/SkiltnummerOrdinærVi_10783.xml">21118</gml:identifier>
			<gml:name>531.112 - Felt for fartsøkning, gjennomg. veg, 1 felt mot, 2 gjennomgående felt i fartsretning</gml:name>
		</gml:Definition>
		<gml:Definition gml:id="21119">
			<gml:description>Felt for fartsøking, gjennomgående veg, motgående trafikk atskilt, 1 gjennomgående felt i fartsretning</gml:description>
			<gml:identifier codeSpace="https://github.com/tonoarmas/kodelister/blob/main/SkiltnummerOrdinærVi_10783.xml">21119</gml:identifier>
			<gml:name>531.113 - Felt for fartsøkning, gjg. veg, 1 felt mot, 3 gjg. felt i fartsretning</gml:name>
		</gml:Definition>
		<gml:Definition gml:id="21120">
			<gml:description>Felt for fartsøkning, gjennomg. veg, 2 felt mot, 1 gjennomgående felt i fartsretning</gml:description>
			<gml:identifier codeSpace="https://github.com/tonoarmas/kodelister/blob/main/SkiltnummerOrdinærVi_10783.xml">21120</gml:identifier>
			<gml:name>531.121 - Felt for fartsøkning, gjennomg. veg, 2 felt mot, 1 gjennomgående felt i fartsretning</gml:name>
		</gml:Definition>
		<gml:Definition gml:id="21121">
			<gml:description>Felt for fartsøkning, gjennomg. veg, 2 felt mot, 2 gjennomgående felt i fartsretning</gml:description>
			<gml:identifier codeSpace="https://github.com/tonoarmas/kodelister/blob/main/SkiltnummerOrdinærVi_10783.xml">21121</gml:identifier>
			<gml:name>531.122 - Felt for fartsøkning, gjennomg. veg, 2 felt mot, 2 gjennomgående felt i fartsretning</gml:name>
		</gml:Definition>
		<gml:Definition gml:id="21122">
			<gml:description>Felt for fartsøkning, gjennomg. veg, 2 felt mot, 3 gjennomgående felt i fartsretning</gml:description>
			<gml:identifier codeSpace="https://github.com/tonoarmas/kodelister/blob/main/SkiltnummerOrdinærVi_10783.xml">21122</gml:identifier>
			<gml:name>531.123 - Felt for fartsøkning, gjennomg. veg, 2 felt mot, 3 gjennomgående felt i fartsretning</gml:name>
		</gml:Definition>
		<gml:Definition gml:id="21123">
			<gml:description>Felt for fartsøkning, tilkjøringsveg, motgående trafikk adskilt, 1 gjennomgående felt i fartsretning</gml:description>
			<gml:identifier codeSpace="https://github.com/tonoarmas/kodelister/blob/main/SkiltnummerOrdinærVi_10783.xml">21123</gml:identifier>
			<gml:name>531.201 - Felt for fartsøkning, tilkjøringsveg, motg. trafikk atskilt, 1 gjg. felt i fartsretn.</gml:name>
		</gml:Definition>
		<gml:Definition gml:id="21124">
			<gml:description>Felt for fartsøkning, tilkjøringsveg, motgående trafikk adskilt, 2 gjennomgående felt i fartsretning</gml:description>
			<gml:identifier codeSpace="https://github.com/tonoarmas/kodelister/blob/main/SkiltnummerOrdinærVi_10783.xml">21124</gml:identifier>
			<gml:name>531.202 - Felt for fartsøkning, tilkjøringsveg, motg. trafikk atskilt, 2 gjg. felt i fartsretn.</gml:name>
		</gml:Definition>
		<gml:Definition gml:id="21125">
			<gml:description>Felt for fartsøkning, tilkjøringsveg, motgående trafikk adskilt, 3 gjennomgående felt i fartsretning</gml:description>
			<gml:identifier codeSpace="https://github.com/tonoarmas/kodelister/blob/main/SkiltnummerOrdinærVi_10783.xml">21125</gml:identifier>
			<gml:name>531.203 - Felt for fartsøkning, tilkjøringsveg, motg. trafikk atskilt, 3 gjg. felt i fartsretn.</gml:name>
		</gml:Definition>
		<gml:Definition gml:id="21126">
			<gml:description>Felt for fartsøkning, tilkjøringsveg, motgående trafikk adskilt, 4 gjennomgående felt i fartsretning</gml:description>
			<gml:identifier codeSpace="https://github.com/tonoarmas/kodelister/blob/main/SkiltnummerOrdinærVi_10783.xml">21126</gml:identifier>
			<gml:name>531.204 - Felt for fartsøkning, tilkjøringsveg, motg. trafikk atskilt, 4 gjg. felt i fartsretn.</gml:name>
		</gml:Definition>
		<gml:Definition gml:id="21127">
			<gml:description>Felt for fartsøkning, tilkjøringsveg, motgående trafikk adskilt, 5 gjennomgående felt i fartsretning</gml:description>
			<gml:identifier codeSpace="https://github.com/tonoarmas/kodelister/blob/main/SkiltnummerOrdinærVi_10783.xml">21127</gml:identifier>
			<gml:name>531.205 - Felt for fartsøkning, tilkj.veg, motg. trafikk atskilt, 5 gjg. felt i fartsretning</gml:name>
		</gml:Definition>
		<gml:Definition gml:id="21128">
			<gml:description>Felt for fartsøkning, tilkjøringsveg, motgående trafikk adskilt, 6 gjennomgående felt i fartsretning</gml:description>
			<gml:identifier codeSpace="https://github.com/tonoarmas/kodelister/blob/main/SkiltnummerOrdinærVi_10783.xml">21128</gml:identifier>
			<gml:name>531.206 - Felt for fartsøkning, tilkj.veg, motg. trafikk atskilt, 6 gjg. felt i fartsretning</gml:name>
		</gml:Definition>
		<gml:Definition gml:id="21129">
			<gml:description>Felt for fartsøkning, tilkjøringsveg, 1 felt mot, 1 gjennomgående felt i fartsretning</gml:description>
			<gml:identifier codeSpace="https://github.com/tonoarmas/kodelister/blob/main/SkiltnummerOrdinærVi_10783.xml">21129</gml:identifier>
			<gml:name>531.211 - Felt for fartsøkning, tilkjøringsveg, 1 felt mot, 1 gjennomgående felt i fartsretning</gml:name>
		</gml:Definition>
		<gml:Definition gml:id="21130">
			<gml:description>Felt for fartsøkning, tilkjøringsveg, 1 felt mot, 2 gjennomgående felt i fartsretning</gml:description>
			<gml:identifier codeSpace="https://github.com/tonoarmas/kodelister/blob/main/SkiltnummerOrdinærVi_10783.xml">21130</gml:identifier>
			<gml:name>531.212 - Felt for fartsøkning, tilkjøringsveg, 1 felt mot, 2 gjennomgående felt i fartsretning</gml:name>
		</gml:Definition>
		<gml:Definition gml:id="21131">
			<gml:description>Felt for fartsøkning, tilkjøringsveg, 1 felt mot, 3 gjennomgående felt i fartsretning</gml:description>
			<gml:identifier codeSpace="https://github.com/tonoarmas/kodelister/blob/main/SkiltnummerOrdinærVi_10783.xml">21131</gml:identifier>
			<gml:name>531.213 - Felt for fartsøkning, tilkjøringsveg, 1 felt mot, 3 gjennomgående felt i fartsretning</gml:name>
		</gml:Definition>
		<gml:Definition gml:id="21132">
			<gml:description>Felt for fartsøkning, tilkjøringsveg, 2 felt mot, 1 gjennomgående felt i fartsretning</gml:description>
			<gml:identifier codeSpace="https://github.com/tonoarmas/kodelister/blob/main/SkiltnummerOrdinærVi_10783.xml">21132</gml:identifier>
			<gml:name>531.221 - Felt for fartsøkning, tilkjøringsveg, 2 felt mot, 1 gjennomgående felt i fartsretning</gml:name>
		</gml:Definition>
		<gml:Definition gml:id="21133">
			<gml:description>Felt for fartsøkning, tilkjøringsveg, 2 felt mot, 2 gjennomgående felt i fartsretning</gml:description>
			<gml:identifier codeSpace="https://github.com/tonoarmas/kodelister/blob/main/SkiltnummerOrdinærVi_10783.xml">21133</gml:identifier>
			<gml:name>531.222 - Felt for fartsøkning, tilkjøringsveg, 2 felt mot, 2 gjennomgående felt i fartsretning</gml:name>
		</gml:Definition>
		<gml:Definition gml:id="21134">
			<gml:description>Felt for fartsøkning, tilkjøringsveg, 2 felt mot, 3 gjennomgående felt i fartsretning</gml:description>
			<gml:identifier codeSpace="https://github.com/tonoarmas/kodelister/blob/main/SkiltnummerOrdinærVi_10783.xml">21134</gml:identifier>
			<gml:name>531.223 - Felt for fartsøkning, tilkjøringsveg, 2 felt mot, 3 gjennomgående felt i fartsretning</gml:name>
		</gml:Definition>
		<gml:Definition gml:id="21135">
			<gml:description>Kjørefelt slutter, høyre side, motgående trafikk adskilt, reduksjon til 1 gjennomgående felt i fartsretning</gml:description>
			<gml:identifier codeSpace="https://github.com/tonoarmas/kodelister/blob/main/SkiltnummerOrdinærVi_10783.xml">21135</gml:identifier>
			<gml:name>532.H01 - Kjf. slutter, høyre side, motg. trafikk atskilt, reduksjon til 1 gjg. felt i fartsretn.</gml:name>
		</gml:Definition>
		<gml:Definition gml:id="21136">
			<gml:description>Kjørefelt slutter, høyre side, motgående trafikk adskilt, reduksjon til 2 gjennomgående felt i fartsretning</gml:description>
			<gml:identifier codeSpace="https://github.com/tonoarmas/kodelister/blob/main/SkiltnummerOrdinærVi_10783.xml">21136</gml:identifier>
			<gml:name>532.H02 - Kjf. slutter, høyre side, motg. trafikk atskilt, reduksjon til 2 gjg. felt i fartsretn.</gml:name>
		</gml:Definition>
		<gml:Definition gml:id="21137">
			<gml:description>Kjørefelt slutter, høyre side, motgående trafikk adskilt, reduksjon til 3 gjennomgående felt i fartsretning</gml:description>
			<gml:identifier codeSpace="https://github.com/tonoarmas/kodelister/blob/main/SkiltnummerOrdinærVi_10783.xml">21137</gml:identifier>
			<gml:name>532.H03 - Kjf. slutter, høyre side, motg. trafikk atskilt, reduksjon til 3 gjg. felt i fartsretn.</gml:name>
		</gml:Definition>
		<gml:Definition gml:id="21138">
			<gml:description>Kjørefelt slutter, høyre side, motgående trafikk adskilt, reduksjon til 4 gjennomgående felt i fartsretning</gml:description>
			<gml:identifier codeSpace="https://github.com/tonoarmas/kodelister/blob/main/SkiltnummerOrdinærVi_10783.xml">21138</gml:identifier>
			<gml:name>532.H04 - Kjf. slutter, høyre side, motg. trafikk atskilt, reduksjon til 4 gjg. felt i fartsretn.</gml:name>
		</gml:Definition>
		<gml:Definition gml:id="21139">
			<gml:description>Kjørefelt slutter, høyre side, motgående trafikk adskilt, reduksjon til 5 gjennomgående felt i fartsretning</gml:description>
			<gml:identifier codeSpace="https://github.com/tonoarmas/kodelister/blob/main/SkiltnummerOrdinærVi_10783.xml">21139</gml:identifier>
			<gml:name>532.H05 - Felt slutter, h. side, motg. trafikk atskilt, reduksjon til 5 gjg. felt i fartsretning</gml:name>
		</gml:Definition>
		<gml:Definition gml:id="21140">
			<gml:description>Kjørefelt slutter, høyre side, motgående trafikk adskilt, reduksjon til 6 gjennomgående felt i fartsretning</gml:description>
			<gml:identifier codeSpace="https://github.com/tonoarmas/kodelister/blob/main/SkiltnummerOrdinærVi_10783.xml">21140</gml:identifier>
			<gml:name>532.H06 - Felt slutter, h. side, motg. trafikk atskilt, reduksjon til 6 gjg. felt i fartsretning</gml:name>
		</gml:Definition>
		<gml:Definition gml:id="21141">
			<gml:description>Kjørefelt slutter, høyre side, 1 felt mot, reduksjon til 1 gjennomgående felt i fartsretning</gml:description>
			<gml:identifier codeSpace="https://github.com/tonoarmas/kodelister/blob/main/SkiltnummerOrdinærVi_10783.xml">21141</gml:identifier>
			<gml:name>532.H11 - Kjf. slutter, høyre side, 1 felt mot, reduksjon til 1 gjg. felt i fartsretn.</gml:name>
		</gml:Definition>
		<gml:Definition gml:id="21142">
			<gml:description>Kjørefelt slutter, høyre side, 1 felt mot, reduksjon til 2 gjennomgående felt i fartsretning.  (Skiltnummer utgått fom ver. 176)</gml:description>
			<gml:identifier codeSpace="https://github.com/tonoarmas/kodelister/blob/main/SkiltnummerOrdinærVi_10783.xml">21142</gml:identifier>
			<gml:name>532.H12 - Felt slutter, h. side, 1 felt mot, reduksjon til 2 gjg. felt i fartsretning</gml:name>
		</gml:Definition>
		<gml:Definition gml:id="21143">
			<gml:description>Kjørefelt slutter, høyre side, 1 felt mot, reduksjon til 3 gjennomgående felt i fartsretning</gml:description>
			<gml:identifier codeSpace="https://github.com/tonoarmas/kodelister/blob/main/SkiltnummerOrdinærVi_10783.xml">21143</gml:identifier>
			<gml:name>532.H13 - Felt slutter, h. side, 1 felt mot, reduksjon til 3 gjg. felt i fartsretning</gml:name>
		</gml:Definition>
		<gml:Definition gml:id="21144">
			<gml:description>Kjørefelt slutter, høyre side, 2 felt mot, reduksjon til 1 gjennomgående felt i fartsretning</gml:description>
			<gml:identifier codeSpace="https://github.com/tonoarmas/kodelister/blob/main/SkiltnummerOrdinærVi_10783.xml">21144</gml:identifier>
			<gml:name>532.H21 - Kjf. slutter, høyre side, 2 felt mot, reduksjon til 1 gjg. felt i fartsretn.</gml:name>
		</gml:Definition>
		<gml:Definition gml:id="21145">
			<gml:description>Kjørefelt slutter, høyre side, 2 felt mot, reduksjon til 2 gjennomgående felt i fartsretning</gml:description>
			<gml:identifier codeSpace="https://github.com/tonoarmas/kodelister/blob/main/SkiltnummerOrdinærVi_10783.xml">21145</gml:identifier>
			<gml:name>532.H22 - Felt slutter, h. side, 2 felt mot, reduksjon til 2 gjg. felt i fartsretning</gml:name>
		</gml:Definition>
		<gml:Definition gml:id="21146">
			<gml:description>Kjørefelt slutter, høyre side, 2 felt mot, reduksjon til 3 gjennomgående felt i fartsretning</gml:description>
			<gml:identifier codeSpace="https://github.com/tonoarmas/kodelister/blob/main/SkiltnummerOrdinærVi_10783.xml">21146</gml:identifier>
			<gml:name>532.H23 - Felt slutter, h. side, 2 felt mot, reduksjon til 3 gjg. felt i fartsretning</gml:name>
		</gml:Definition>
		<gml:Definition gml:id="21147">
			<gml:description>Kjørefelt slutter, venstre side, motgående trafikk adskilt, reduksjon til 1 gjennomgående felt i fartsretning</gml:description>
			<gml:identifier codeSpace="https://github.com/tonoarmas/kodelister/blob/main/SkiltnummerOrdinærVi_10783.xml">21147</gml:identifier>
			<gml:name>532.V01 - Kjf. slutter, venstre side, motg. trafikk atskilt, reduksjon til 1 gjg. felt i fartsretn.</gml:name>
		</gml:Definition>
		<gml:Definition gml:id="21148">
			<gml:description>Kjørefelt slutter, venstre side, motgående trafikk adskilt, reduksjon til 2 gjennomgående felt i fartsretning</gml:description>
			<gml:identifier codeSpace="https://github.com/tonoarmas/kodelister/blob/main/SkiltnummerOrdinærVi_10783.xml">21148</gml:identifier>
			<gml:name>532.V02 - Kjf. slutter, venstre side, motg. trafikk atskilt, reduksjon til 2 gjg. felt i fartsretn.</gml:name>
		</gml:Definition>
		<gml:Definition gml:id="21149">
			<gml:description>Kjørefelt slutter, venstre side, motgående trafikk adskilt, reduksjon til 3 gjennomgående felt i fartsretning</gml:description>
			<gml:identifier codeSpace="https://github.com/tonoarmas/kodelister/blob/main/SkiltnummerOrdinærVi_10783.xml">21149</gml:identifier>
			<gml:name>532.V03 - Kjf. slutter, venstre side, motg. trafikk atskilt, reduksjon til 3 gjg. felt i fartsretn.</gml:name>
		</gml:Definition>
		<gml:Definition gml:id="21150">
			<gml:description>Kjørefelt slutter, venstre side, motgående trafikk adskilt, reduksjon til 4 gjennomgående felt i fartsretning</gml:description>
			<gml:identifier codeSpace="https://github.com/tonoarmas/kodelister/blob/main/SkiltnummerOrdinærVi_10783.xml">21150</gml:identifier>
			<gml:name>532.V04 - Kjf. slutter, venstre side, motg. trafikk atskilt, reduksjon til 4 gjg. felt i fartsretn.</gml:name>
		</gml:Definition>
		<gml:Definition gml:id="21151">
			<gml:description>Kjørefelt slutter, venstre side, motgående trafikk adskilt, reduksjon til 5 gjennomgående felt i fartsretning</gml:description>
			<gml:identifier codeSpace="https://github.com/tonoarmas/kodelister/blob/main/SkiltnummerOrdinærVi_10783.xml">21151</gml:identifier>
			<gml:name>532.V05 - Felt slutter, v. side, motg. trafikk atskilt, reduksjon til 5 gjg. felt i fartsretning</gml:name>
		</gml:Definition>
		<gml:Definition gml:id="21152">
			<gml:description>Kjørefelt slutter, venstre side, motgående trafikk adskilt, reduksjon til 6 gjennomgående felt i fartsretning</gml:description>
			<gml:identifier codeSpace="https://github.com/tonoarmas/kodelister/blob/main/SkiltnummerOrdinærVi_10783.xml">21152</gml:identifier>
			<gml:name>532.V06 - Felt slutter, v. side, motg. trafikk atskilt, reduksjon til 6 gjg. felt i fartsretning</gml:name>
		</gml:Definition>
		<gml:Definition gml:id="21153">
			<gml:description>Kjørefelt slutter, venstre side, 1 felt mot, reduksjon til 1 gjennomgående felt i fartsretning</gml:description>
			<gml:identifier codeSpace="https://github.com/tonoarmas/kodelister/blob/main/SkiltnummerOrdinærVi_10783.xml">21153</gml:identifier>
			<gml:name>532.V11 - Kjf. slutter, venstre side, 1 felt mot, reduksjon til 1 gjg. felt i fartsretn.</gml:name>
		</gml:Definition>
		<gml:Definition gml:id="21154">
			<gml:description>Kjørefelt slutter, venstre side, 1 felt mot, reduksjon til 2 gjennomgående felt i fartsretning</gml:description>
			<gml:identifier codeSpace="https://github.com/tonoarmas/kodelister/blob/main/SkiltnummerOrdinærVi_10783.xml">21154</gml:identifier>
			<gml:name>532.V12 - Felt slutter, v. side, 1 felt mot, reduksjon til 2 gjg. felt i fartsretning</gml:name>
		</gml:Definition>
		<gml:Definition gml:id="21155">
			<gml:description>Kjørefelt slutter, venstre side, 1 felt mot, reduksjon til 3 gjennomgående felt i fartsretning</gml:description>
			<gml:identifier codeSpace="https://github.com/tonoarmas/kodelister/blob/main/SkiltnummerOrdinærVi_10783.xml">21155</gml:identifier>
			<gml:name>532.V13 - Felt slutter, v. side, 1 felt mot, reduksjon til 3 gjg. felt i fartsretning</gml:name>
		</gml:Definition>
		<gml:Definition gml:id="21156">
			<gml:description>Kjørefelt slutter, venstre side, 2 felt mot, reduksjon til 1 gjennomgående felt i fartsretning</gml:description>
			<gml:identifier codeSpace="https://github.com/tonoarmas/kodelister/blob/main/SkiltnummerOrdinærVi_10783.xml">21156</gml:identifier>
			<gml:name>532.V21 - Kjf. slutter, venstre side, 2 felt mot, reduksjon til 1 gjg. felt i fartsretn.</gml:name>
		</gml:Definition>
		<gml:Definition gml:id="21157">
			<gml:description>Kjørefelt slutter, venstre side, 2 felt mot, reduksjon til 2 gjennomgående felt i fartsretning</gml:description>
			<gml:identifier codeSpace="https://github.com/tonoarmas/kodelister/blob/main/SkiltnummerOrdinærVi_10783.xml">21157</gml:identifier>
			<gml:name>532.V22 - Felt slutter, v. side, 2 felt mot, reduksjon til 2 gjg. felt i fartsretning</gml:name>
		</gml:Definition>
		<gml:Definition gml:id="21158">
			<gml:description>Kjørefelt slutter, venstre side, 2 felt mot, reduksjon til 3 gjennomgående felt i fartsretning</gml:description>
			<gml:identifier codeSpace="https://github.com/tonoarmas/kodelister/blob/main/SkiltnummerOrdinærVi_10783.xml">21158</gml:identifier>
			<gml:name>532.V23 - Felt slutter, v. side, 2 felt mot, reduksjon til 3 gjg. felt i fartsretning</gml:name>
		</gml:Definition>
		<gml:Definition gml:id="21159">
			<gml:description>Kjørefelt begynner, høyre side, motgående trafikk adskilt, 1 gjennomgående felt i fartsretning</gml:description>
			<gml:identifier codeSpace="https://github.com/tonoarmas/kodelister/blob/main/SkiltnummerOrdinærVi_10783.xml">21159</gml:identifier>
			<gml:name>534.H01 - Kjf. beg., høyre side, motg. trafikk atskilt, 1 gjg. felt i fartsretn.</gml:name>
		</gml:Definition>
		<gml:Definition gml:id="21160">
			<gml:description>Kjørefelt begynner, høyre side, motgående trafikk adskilt, 2 gjennomgående felt i fartsretning</gml:description>
			<gml:identifier codeSpace="https://github.com/tonoarmas/kodelister/blob/main/SkiltnummerOrdinærVi_10783.xml">21160</gml:identifier>
			<gml:name>534.H02 - Kjf. beg., høyre side, motg. trafikk atskilt, 2 gjg. felt i fartsretn.</gml:name>
		</gml:Definition>
		<gml:Definition gml:id="21161">
			<gml:description>Kjørefelt begynner, høyre side, motgående trafikk adskilt, 3 gjennomgående felt i fartsretning</gml:description>
			<gml:identifier codeSpace="https://github.com/tonoarmas/kodelister/blob/main/SkiltnummerOrdinærVi_10783.xml">21161</gml:identifier>
			<gml:name>534.H03 - Kjf. beg., høyre side, motg. trafikk atskilt, 3 gjg. felt i fartsretn.</gml:name>
		</gml:Definition>
		<gml:Definition gml:id="21162">
			<gml:description>Kjørefelt begynner, høyre side, motgående trafikk adskilt, 4 gjennomgående felt i fartsretning</gml:description>
			<gml:identifier codeSpace="https://github.com/tonoarmas/kodelister/blob/main/SkiltnummerOrdinærVi_10783.xml">21162</gml:identifier>
			<gml:name>534.H04 - Kjf. beg., høyre side, motg. trafikk atskilt, 4 gjg. felt i fartsretn.</gml:name>
		</gml:Definition>
		<gml:Definition gml:id="21163">
			<gml:description>Kjørefelt begynner, høyre side, motgående trafikk adskilt, 5 gjennomgående felt i fartsretning</gml:description>
			<gml:identifier codeSpace="https://github.com/tonoarmas/kodelister/blob/main/SkiltnummerOrdinærVi_10783.xml">21163</gml:identifier>
			<gml:name>534.H05 - Felt begynner, h. side, motg. trafikk atskilt, 5 gjg. felt i fartsretning</gml:name>
		</gml:Definition>
		<gml:Definition gml:id="21164">
			<gml:description>Kjørefelt begynner, høyre side, motgående trafikk adskilt, 6 gjennomgående felt i fartsretning</gml:description>
			<gml:identifier codeSpace="https://github.com/tonoarmas/kodelister/blob/main/SkiltnummerOrdinærVi_10783.xml">21164</gml:identifier>
			<gml:name>534.H06 - Felt begynner, h. side, motg. trafikk atskilt, 6 gjg. felt i fartsretning</gml:name>
		</gml:Definition>
		<gml:Definition gml:id="21165">
			<gml:description>Kjørefelt begynner, høyre side, 1 felt mot, 1 gjennomgående felt i fartsretning</gml:description>
			<gml:identifier codeSpace="https://github.com/tonoarmas/kodelister/blob/main/SkiltnummerOrdinærVi_10783.xml">21165</gml:identifier>
			<gml:name>534.H11 - Kjørefelt begynner, høyre side, 1 felt mot, 1 gjennomgående felt i fartsretning</gml:name>
		</gml:Definition>
		<gml:Definition gml:id="21166">
			<gml:description>Kjørefelt begynner, høyre side, 1 felt mot, 2 gjennomgående felt i fartsretning</gml:description>
			<gml:identifier codeSpace="https://github.com/tonoarmas/kodelister/blob/main/SkiltnummerOrdinærVi_10783.xml">21166</gml:identifier>
			<gml:name>534.H12 - Kjørefelt begynner, høyre side, 1 felt mot, 2 gjennomgående felt i fartsretning</gml:name>
		</gml:Definition>
		<gml:Definition gml:id="21167">
			<gml:description>Kjørefelt begynner, høyre side, 1 felt mot, 3 gjennomgående felt i fartsretning</gml:description>
			<gml:identifier codeSpace="https://github.com/tonoarmas/kodelister/blob/main/SkiltnummerOrdinærVi_10783.xml">21167</gml:identifier>
			<gml:name>534.H13 - Kjørefelt begynner, høyre side, 1 felt mot, 3 gjennomgående felt i fartsretning</gml:name>
		</gml:Definition>
		<gml:Definition gml:id="21168">
			<gml:description>Kjørefelt begynner, høyre side, 2 felt mot, 1 gjennomgående felt i fartsretning</gml:description>
			<gml:identifier codeSpace="https://github.com/tonoarmas/kodelister/blob/main/SkiltnummerOrdinærVi_10783.xml">21168</gml:identifier>
			<gml:name>534.H21 - Kjørefelt begynner, høyre side, 2 felt mot, 1 gjennomgående felt i fartsretning</gml:name>
		</gml:Definition>
		<gml:Definition gml:id="21169">
			<gml:description>Kjørefelt begynner, høyre side, 2 felt mot, 2 gjennomgående felt i fartsretning</gml:description>
			<gml:identifier codeSpace="https://github.com/tonoarmas/kodelister/blob/main/SkiltnummerOrdinærVi_10783.xml">21169</gml:identifier>
			<gml:name>534.H22 - Kjørefelt begynner, høyre side, 2 felt mot, 2 gjennomgående felt i fartsretning</gml:name>
		</gml:Definition>
		<gml:Definition gml:id="21170">
			<gml:description>Kjørefelt begynner, høyre side, 2 felt mot, 3 gjennomgående felt i fartsretning</gml:description>
			<gml:identifier codeSpace="https://github.com/tonoarmas/kodelister/blob/main/SkiltnummerOrdinærVi_10783.xml">21170</gml:identifier>
			<gml:name>534.H23 - Kjørefelt begynner, høyre side, 2 felt mot, 3 gjennomgående felt i fartsretning</gml:name>
		</gml:Definition>
		<gml:Definition gml:id="21171">
			<gml:description>Kjørefelt begynner, venstre side, motgående trafikk adskilt, 1 gjennomgående felt i fartsretning</gml:description>
			<gml:identifier codeSpace="https://github.com/tonoarmas/kodelister/blob/main/SkiltnummerOrdinærVi_10783.xml">21171</gml:identifier>
			<gml:name>534.V01 - Kjf. beg., venstre side, motg. trafikk atskilt, 1 gjg. felt i fartsretn.</gml:name>
		</gml:Definition>
		<gml:Definition gml:id="21172">
			<gml:description>Kjørefelt begynner, venstre side, motgående trafikk adskilt, 2 gjennomgående felt i fartsretning</gml:description>
			<gml:identifier codeSpace="https://github.com/tonoarmas/kodelister/blob/main/SkiltnummerOrdinærVi_10783.xml">21172</gml:identifier>
			<gml:name>534.V02 - Kjf. beg., venstre side, motg. trafikk atskilt, 2 gjg. felt i fartsretn.</gml:name>
		</gml:Definition>
		<gml:Definition gml:id="21173">
			<gml:description>Kjørefelt begynner, venstre side, motgående trafikk adskilt, 3 gjennomgående felt i fartsretning</gml:description>
			<gml:identifier codeSpace="https://github.com/tonoarmas/kodelister/blob/main/SkiltnummerOrdinærVi_10783.xml">21173</gml:identifier>
			<gml:name>534.V03 - Kjf. beg., venstre side, motg. trafikk atskilt, 3 gjg. felt i fartsretn.</gml:name>
		</gml:Definition>
		<gml:Definition gml:id="21174">
			<gml:description>Kjørefelt begynner, venstre side, motgående trafikk adskilt, 4 gjennomgående felt i fartsretning</gml:description>
			<gml:identifier codeSpace="https://github.com/tonoarmas/kodelister/blob/main/SkiltnummerOrdinærVi_10783.xml">21174</gml:identifier>
			<gml:name>534.V04 - Kjf. beg., venstre side, motg. trafikk atskilt, 4 gjg. felt i fartsretn.</gml:name>
		</gml:Definition>
		<gml:Definition gml:id="21175">
			<gml:description>Kjørefelt begynner, venstre side, motgående trafikk adskilt, 5 gjennomgående felt i fartsretning</gml:description>
			<gml:identifier codeSpace="https://github.com/tonoarmas/kodelister/blob/main/SkiltnummerOrdinærVi_10783.xml">21175</gml:identifier>
			<gml:name>534.V05 - Felt begynner, v. side, motg. trafikk atskilt, 5 gjg. felt i fartsretning</gml:name>
		</gml:Definition>
		<gml:Definition gml:id="21176">
			<gml:description>Kjørefelt begynner, venstre side, motgående trafikk adskilt, 6 gjennomgående felt i fartsretning</gml:description>
			<gml:identifier codeSpace="https://github.com/tonoarmas/kodelister/blob/main/SkiltnummerOrdinærVi_10783.xml">21176</gml:identifier>
			<gml:name>534.V06 - Felt begynner, v. side, motg. trafikk atskilt, 6 gjg. felt i fartsretning</gml:name>
		</gml:Definition>
		<gml:Definition gml:id="21177">
			<gml:description>Kjørefelt begynner, venstre side, 1 felt mot, 1 gjennomgående felt i fartsretning</gml:description>
			<gml:identifier codeSpace="https://github.com/tonoarmas/kodelister/blob/main/SkiltnummerOrdinærVi_10783.xml">21177</gml:identifier>
			<gml:name>534.V11 - Kjørefelt begynner, venstre side, 1 felt mot, 1 gjennomgående felt i fartsretning</gml:name>
		</gml:Definition>
		<gml:Definition gml:id="21178">
			<gml:description>Kjørefelt begynner, venstre side, 1 felt mot, 2 gjennomgående felt i fartsretning</gml:description>
			<gml:identifier codeSpace="https://github.com/tonoarmas/kodelister/blob/main/SkiltnummerOrdinærVi_10783.xml">21178</gml:identifier>
			<gml:name>534.V12 - Kjørefelt begynner, venstre side, 1 felt mot, 2 gjennomgående felt i fartsretning</gml:name>
		</gml:Definition>
		<gml:Definition gml:id="21179">
			<gml:description>Kjørefelt begynner, venstre side, 1 felt mot, 3 gjennomgående felt i fartsretning</gml:description>
			<gml:identifier codeSpace="https://github.com/tonoarmas/kodelister/blob/main/SkiltnummerOrdinærVi_10783.xml">21179</gml:identifier>
			<gml:name>534.V13 - Kjørefelt begynner, venstre side, 1 felt mot, 3 gjennomgående felt i fartsretning</gml:name>
		</gml:Definition>
		<gml:Definition gml:id="21180">
			<gml:description>Kjørefelt begynner, venstre side, 2 felt mot, 1 gjennomgående felt i fartsretning</gml:description>
			<gml:identifier codeSpace="https://github.com/tonoarmas/kodelister/blob/main/SkiltnummerOrdinærVi_10783.xml">21180</gml:identifier>
			<gml:name>534.V21 - Kjørefelt begynner, venstre side, 2 felt mot, 1 gjennomgående felt i fartsretning</gml:name>
		</gml:Definition>
		<gml:Definition gml:id="21181">
			<gml:description>Kjørefelt begynner, venstre side, 2 felt mot, 2 gjennomgående felt i fartsretning</gml:description>
			<gml:identifier codeSpace="https://github.com/tonoarmas/kodelister/blob/main/SkiltnummerOrdinærVi_10783.xml">21181</gml:identifier>
			<gml:name>534.V22 - Kjørefelt begynner, venstre side, 2 felt mot, 2 gjennomgående felt i fartsretning</gml:name>
		</gml:Definition>
		<gml:Definition gml:id="21182">
			<gml:description>Kjørefelt begynner, venstre side, 2 felt mot, 3 gjennomgående felt i fartsretning</gml:description>
			<gml:identifier codeSpace="https://github.com/tonoarmas/kodelister/blob/main/SkiltnummerOrdinærVi_10783.xml">21182</gml:identifier>
			<gml:name>534.V23 - Kjørefelt begynner, venstre side, 2 felt mot, 3 gjennomgående felt i fartsretning</gml:name>
		</gml:Definition>
		<gml:Definition gml:id="21183">
			<gml:description>Påkjøring fortsetter i eget kjørefelt, gjennomg. veg, motgående trafikk adskilt, 1 gjennomgående felt i fartsretning</gml:description>
			<gml:identifier codeSpace="https://github.com/tonoarmas/kodelister/blob/main/SkiltnummerOrdinærVi_10783.xml">21183</gml:identifier>
			<gml:name>536.101 - Påkj. forts. i eget kjf., gjg. veg, motg. trafikk atskilt, 1 gjg. felt i fartsretn.</gml:name>
		</gml:Definition>
		<gml:Definition gml:id="21184">
			<gml:description>Påkjøring fortsetter i eget kjørefelt, gjennomg. veg, motgående trafikk adskilt, 2 gjennomgående felt i fartsretning</gml:description>
			<gml:identifier codeSpace="https://github.com/tonoarmas/kodelister/blob/main/SkiltnummerOrdinærVi_10783.xml">21184</gml:identifier>
			<gml:name>536.102 - Påkj. forts. i eget kjf., gjg. veg, motg. trafikk atskilt, 2 gjg. felt i fartsretn.</gml:name>
		</gml:Definition>
		<gml:Definition gml:id="21185">
			<gml:description>Påkjøring fortsetter i eget kjørefelt, gjennomg. veg, motgående trafikk adskilt, 3 gjennomgående felt i fartsretning</gml:description>
			<gml:identifier codeSpace="https://github.com/tonoarmas/kodelister/blob/main/SkiltnummerOrdinærVi_10783.xml">21185</gml:identifier>
			<gml:name>536.103 - Påkj. forts. i eget kjf., gjg. veg, motg. trafikk atskilt, 3 gjg. felt i fartsretn.</gml:name>
		</gml:Definition>
		<gml:Definition gml:id="21186">
			<gml:description>Påkjøring fortsetter i eget kjørefelt, gjennomg. veg, motgående trafikk adskilt, 4 gjennomgående felt i fartsretning</gml:description>
			<gml:identifier codeSpace="https://github.com/tonoarmas/kodelister/blob/main/SkiltnummerOrdinærVi_10783.xml">21186</gml:identifier>
			<gml:name>536.104 - Påkj. forts. i eget kjf., gjg. veg, motg. trafikk atskilt, 4 gjg. felt i fartsretn.</gml:name>
		</gml:Definition>
		<gml:Definition gml:id="21187">
			<gml:description>Påkjøring fortsetter i eget kjørefelt, gjennomg. veg, motgående trafikk adskilt, 5 gjennomgående felt i fartsretning</gml:description>
			<gml:identifier codeSpace="https://github.com/tonoarmas/kodelister/blob/main/SkiltnummerOrdinærVi_10783.xml">21187</gml:identifier>
			<gml:name>536.105 - Påkjøring forts. i eget felt, gjg. veg, motg. trafikk atskilt, 5 gjg. felt i fartsretning</gml:name>
		</gml:Definition>
		<gml:Definition gml:id="21188">
			<gml:description>Påkjøring fortsetter i eget kjørefelt, gjennomg. veg, motgående trafikk adskilt, 6 gjennomgående felt i fartsretning</gml:description>
			<gml:identifier codeSpace="https://github.com/tonoarmas/kodelister/blob/main/SkiltnummerOrdinærVi_10783.xml">21188</gml:identifier>
			<gml:name>536.106 - Påkjøring forts. i eget felt, gjg. veg, motg. trafikk atskilt, 6 gjg. felt i fartsretning</gml:name>
		</gml:Definition>
		<gml:Definition gml:id="21189">
			<gml:description>Påkjøring fortsetter i eget kjørefelt, gjennomg. veg, 1 felt mot, 1 gjennomgående felt i fartsretning</gml:description>
			<gml:identifier codeSpace="https://github.com/tonoarmas/kodelister/blob/main/SkiltnummerOrdinærVi_10783.xml">21189</gml:identifier>
			<gml:name>536.111 - Påkj. forts. i eget kjf., gjg. veg, 1 felt mot 1, gjg. felt i fartsretn.</gml:name>
		</gml:Definition>
		<gml:Definition gml:id="21190">
			<gml:description>Påkjøring fortsetter i eget kjørefelt, gjennomg. veg, 1 felt mot, 2 gjennomgående felt i fartsretning</gml:description>
			<gml:identifier codeSpace="https://github.com/tonoarmas/kodelister/blob/main/SkiltnummerOrdinærVi_10783.xml">21190</gml:identifier>
			<gml:name>536.112 - Påkjøring forts. i eget felt, gjg. veg, 1 felt mot, 2 gjg. felt i fartsretning</gml:name>
		</gml:Definition>
		<gml:Definition gml:id="21191">
			<gml:description>Påkjøring fortsetter i eget kjørefelt, gjennomg. veg, 1 felt mot, 3 gjennomgående felt i fartsretning</gml:description>
			<gml:identifier codeSpace="https://github.com/tonoarmas/kodelister/blob/main/SkiltnummerOrdinærVi_10783.xml">21191</gml:identifier>
			<gml:name>536.113 - Påkjøring forts. i eget felt, gjg. veg, 1 felt mot, 3 gjg. felt i fartsretning</gml:name>
		</gml:Definition>
		<gml:Definition gml:id="21192">
			<gml:description>Påkjøring fortsetter i eget kjørefelt, gjennomg. veg, 2 felt mot, 1 gjennomgående felt i fartsretning</gml:description>
			<gml:identifier codeSpace="https://github.com/tonoarmas/kodelister/blob/main/SkiltnummerOrdinærVi_10783.xml">21192</gml:identifier>
			<gml:name>536.121 - Påkj. forts. i eget kjf., gjg. veg, 2 felt mot 1, gjg. felt i fartsretn.</gml:name>
		</gml:Definition>
		<gml:Definition gml:id="21193">
			<gml:description>Påkjøring fortsetter i eget kjørefelt, gjennomg. veg, 2 felt mot, 2 gjennomgående felt i fartsretning</gml:description>
			<gml:identifier codeSpace="https://github.com/tonoarmas/kodelister/blob/main/SkiltnummerOrdinærVi_10783.xml">21193</gml:identifier>
			<gml:name>536.122 - Påkjøring forts. i eget felt, gjg. veg, 2 felt mot, 2 gjg. felt i fartsretning</gml:name>
		</gml:Definition>
		<gml:Definition gml:id="21194">
			<gml:description>Påkjøring fortsetter i eget kjørefelt, gjennomg. veg, 2 felt mot, 3 gjennomgående felt i fartsretning</gml:description>
			<gml:identifier codeSpace="https://github.com/tonoarmas/kodelister/blob/main/SkiltnummerOrdinærVi_10783.xml">21194</gml:identifier>
			<gml:name>536.123 - Påkjøring forts. i eget felt, gjg. veg, 2 felt mot, 3 gjg. felt i fartsretning</gml:name>
		</gml:Definition>
		<gml:Definition gml:id="21195">
			<gml:description>Påkjøring fortsetter i eget kjørefelt, tilkjøringsveg, motgående trafikk adskilt, 1 gjennomgående felt i fartsretning</gml:description>
			<gml:identifier codeSpace="https://github.com/tonoarmas/kodelister/blob/main/SkiltnummerOrdinærVi_10783.xml">21195</gml:identifier>
			<gml:name>536.201 - Påkj. forts. i eget kjf., tilkjøringsveg, motg. trafikk atskilt, 1 gjg. felt i fartsretn.</gml:name>
		</gml:Definition>
		<gml:Definition gml:id="21196">
			<gml:description>Påkjøring fortsetter i eget kjørefelt, tilkjøringsveg, motgående trafikk adskilt, 2 gjennomgående felt i fartsretning</gml:description>
			<gml:identifier codeSpace="https://github.com/tonoarmas/kodelister/blob/main/SkiltnummerOrdinærVi_10783.xml">21196</gml:identifier>
			<gml:name>536.202 - Påkj. forts. i eget kjf., tilkjøringsveg, motg. trafikk atskilt, 2 gjg. felt i fartsretn.</gml:name>
		</gml:Definition>
		<gml:Definition gml:id="21197">
			<gml:description>Påkjøring fortsetter i eget kjørefelt, tilkjøringsveg, motgående trafikk adskilt, 3 gjennomgående felt i fartsretning</gml:description>
			<gml:identifier codeSpace="https://github.com/tonoarmas/kodelister/blob/main/SkiltnummerOrdinærVi_10783.xml">21197</gml:identifier>
			<gml:name>536.203 - Påkj. forts. i eget kjf., tilkjøringsveg, motg. trafikk atskilt, 3 gjg. felt i fartsretn.</gml:name>
		</gml:Definition>
		<gml:Definition gml:id="21198">
			<gml:description>Påkjøring fortsetter i eget kjørefelt, tilkjøringsveg, motgående trafikk adskilt, 4 gjennomgående felt i fartsretning</gml:description>
			<gml:identifier codeSpace="https://github.com/tonoarmas/kodelister/blob/main/SkiltnummerOrdinærVi_10783.xml">21198</gml:identifier>
			<gml:name>536.204 - Påkj. forts. i eget kjf., tilkjøringsveg, motg. trafikk atskilt, 4 gjg. felt i fartsretn.</gml:name>
		</gml:Definition>
		<gml:Definition gml:id="21199">
			<gml:description>Påkjøring fortsetter i eget kjørefelt, tilkjøringsveg, motgående trafikk adskilt, 5 gjennomgående felt i fartsretning</gml:description>
			<gml:identifier codeSpace="https://github.com/tonoarmas/kodelister/blob/main/SkiltnummerOrdinærVi_10783.xml">21199</gml:identifier>
			<gml:name>536.205 - Påkjøring forts. i eget felt, tilkj.veg, motg. trafikk adsk., 5 gjg. felt i fartsretning</gml:name>
		</gml:Definition>
		<gml:Definition gml:id="21200">
			<gml:description>Påkjøring fortsetter i eget kjørefelt, tilkjøringsveg, motgående trafikk adskilt, 6 gjennomgående felt i fartsretning</gml:description>
			<gml:identifier codeSpace="https://github.com/tonoarmas/kodelister/blob/main/SkiltnummerOrdinærVi_10783.xml">21200</gml:identifier>
			<gml:name>536.206 - Påkjøring forts. i eget felt, tilkj.veg, motg. trafikk adsk., 6 gjg. felt i fartsretning</gml:name>
		</gml:Definition>
		<gml:Definition gml:id="21201">
			<gml:description>Påkjøring fortsetter i eget kjørefelt, tilkjøringsveg, 1 felt mot, 1 gjennomgående felt i fartsretning</gml:description>
			<gml:identifier codeSpace="https://github.com/tonoarmas/kodelister/blob/main/SkiltnummerOrdinærVi_10783.xml">21201</gml:identifier>
			<gml:name>536.211 - Påkj. forts. i eget kjf., tilkjøringsveg, 1 felt mot 1, gjg. felt i fartsretn.</gml:name>
		</gml:Definition>
		<gml:Definition gml:id="21202">
			<gml:description>Påkjøring fortsetter i eget kjørefelt, tilkjøringsveg, 1 felt mot, 2 gjennomgående felt i fartsretning</gml:description>
			<gml:identifier codeSpace="https://github.com/tonoarmas/kodelister/blob/main/SkiltnummerOrdinærVi_10783.xml">21202</gml:identifier>
			<gml:name>536.212 - Påkjøring forts. i eget felt, tilkj.veg, 1 felt mot, 2 gjg. felt i fartsretning</gml:name>
		</gml:Definition>
		<gml:Definition gml:id="21203">
			<gml:description>Påkjøring fortsetter i eget kjørefelt, tilkjøringsveg, 1 felt mot, 3 gjennomgående felt i fartsretning</gml:description>
			<gml:identifier codeSpace="https://github.com/tonoarmas/kodelister/blob/main/SkiltnummerOrdinærVi_10783.xml">21203</gml:identifier>
			<gml:name>536.213 - Påkjøring forts. i eget felt, tilkj.veg, 1 felt mot, 3 gjg. felt i fartsretning</gml:name>
		</gml:Definition>
		<gml:Definition gml:id="21204">
			<gml:description>Påkjøring fortsetter i eget kjørefelt, tilkjøringsveg, 2 felt mot, 1 gjennomgående felt i fartsretning</gml:description>
			<gml:identifier codeSpace="https://github.com/tonoarmas/kodelister/blob/main/SkiltnummerOrdinærVi_10783.xml">21204</gml:identifier>
			<gml:name>536.221 - Påkj. forts. i eget kjf., tilkjøringsveg, 2 felt mot 1, gjg. felt i fartsretn.</gml:name>
		</gml:Definition>
		<gml:Definition gml:id="21205">
			<gml:description>Påkjøring fortsetter i eget kjørefelt, tilkjøringsveg, 2 felt mot, 2 gjennomgående felt i fartsretning</gml:description>
			<gml:identifier codeSpace="https://github.com/tonoarmas/kodelister/blob/main/SkiltnummerOrdinærVi_10783.xml">21205</gml:identifier>
			<gml:name>536.222 - Påkjøring forts. i eget felt, tilkj.veg, 2 felt mot, 2 gjg. felt i fartsretning</gml:name>
		</gml:Definition>
		<gml:Definition gml:id="21206">
			<gml:description>Påkjøring fortsetter i eget kjørefelt, tilkjøringsveg, 2 felt mot, 3 gjennomgående felt i fartsretning</gml:description>
			<gml:identifier codeSpace="https://github.com/tonoarmas/kodelister/blob/main/SkiltnummerOrdinærVi_10783.xml">21206</gml:identifier>
			<gml:name>536.223 - Påkjøring forts. i eget felt, tilkj.veg, 2 felt mot, 3 gjg. felt i fartsretning</gml:name>
		</gml:Definition>
		<gml:Definition gml:id="21207">
			<gml:description>Kjørefeltinndeling, motgående trafikk adskilt, 2 gjennomgående felt i fartsretning</gml:description>
			<gml:identifier codeSpace="https://github.com/tonoarmas/kodelister/blob/main/SkiltnummerOrdinærVi_10783.xml">21207</gml:identifier>
			<gml:name>538.02 - Kjørefeltinndeling, motgående trafikk adskilt, 2 gjennomgående felt i fartsretning</gml:name>
		</gml:Definition>
		<gml:Definition gml:id="21208">
			<gml:description>Kjørefeltinndeling, motgående trafikk adskilt, 3 gjennomgående felt i fartsretning</gml:description>
			<gml:identifier codeSpace="https://github.com/tonoarmas/kodelister/blob/main/SkiltnummerOrdinærVi_10783.xml">21208</gml:identifier>
			<gml:name>538.03 - Kjørefeltinndeling, motgående trafikk adskilt, 3 gjennomgående felt i fartsretning</gml:name>
		</gml:Definition>
		<gml:Definition gml:id="21209">
			<gml:description>Kjørefeltinndeling, motgående trafikk adskilt, 4 gjennomgående felt i fartsretning</gml:description>
			<gml:identifier codeSpace="https://github.com/tonoarmas/kodelister/blob/main/SkiltnummerOrdinærVi_10783.xml">21209</gml:identifier>
			<gml:name>538.04 - Kjørefeltinndeling, motgående trafikk adskilt, 4 gjennomgående felt i fartsretning</gml:name>
		</gml:Definition>
		<gml:Definition gml:id="21210">
			<gml:description>Kjørefeltinndeling, motgående trafikk adskilt, 5 gjennomgående felt i fartsretning</gml:description>
			<gml:identifier codeSpace="https://github.com/tonoarmas/kodelister/blob/main/SkiltnummerOrdinærVi_10783.xml">21210</gml:identifier>
			<gml:name>538.05 - Kjørefeltinndeling, motgående trafikk adskilt, 5 gjennomgående felt i fartsretning</gml:name>
		</gml:Definition>
		<gml:Definition gml:id="21211">
			<gml:description>Kjørefeltinndeling, motgående trafikk adskilt, 6 gjennomgående felt i fartsretning</gml:description>
			<gml:identifier codeSpace="https://github.com/tonoarmas/kodelister/blob/main/SkiltnummerOrdinærVi_10783.xml">21211</gml:identifier>
			<gml:name>538.06 - Kjørefeltinndeling, motgående trafikk adskilt, 6 gjennomgående felt i fartsretning</gml:name>
		</gml:Definition>
		<gml:Definition gml:id="21212">
			<gml:description>Kjørefeltinndeling, 1 felt mot, 2 gjennomgående felt i fartsretning</gml:description>
			<gml:identifier codeSpace="https://github.com/tonoarmas/kodelister/blob/main/SkiltnummerOrdinærVi_10783.xml">21212</gml:identifier>
			<gml:name>538.12 - Kjørefeltinndeling, 1 felt mot, 2 gjennomgående felt i fartsretning</gml:name>
		</gml:Definition>
		<gml:Definition gml:id="21213">
			<gml:description>Kjørefeltinndeling, 1 felt mot, 3 gjennomgående felt i fartsretning</gml:description>
			<gml:identifier codeSpace="https://github.com/tonoarmas/kodelister/blob/main/SkiltnummerOrdinærVi_10783.xml">21213</gml:identifier>
			<gml:name>538.13 - Kjørefeltinndeling, 1 felt mot, 3 gjennomgående felt i fartsretning</gml:name>
		</gml:Definition>
		<gml:Definition gml:id="21214">
			<gml:description>Kjørefeltinndeling, 2 felt mot, 1 gjennomgående felt i fartsretning</gml:description>
			<gml:identifier codeSpace="https://github.com/tonoarmas/kodelister/blob/main/SkiltnummerOrdinærVi_10783.xml">21214</gml:identifier>
			<gml:name>538.21 - Kjørefeltinndeling, 2 felt mot, 1 gjennomgående felt i fartsretning</gml:name>
		</gml:Definition>
		<gml:Definition gml:id="21215">
			<gml:description>Kjørefeltinndeling, 2 felt mot, 2 gjennomgående felt i fartsretning</gml:description>
			<gml:identifier codeSpace="https://github.com/tonoarmas/kodelister/blob/main/SkiltnummerOrdinærVi_10783.xml">21215</gml:identifier>
			<gml:name>538.22 - Kjørefeltinndeling, 2 felt mot, 2 gjennomgående felt i fartsretning</gml:name>
		</gml:Definition>
		<gml:Definition gml:id="21216">
			<gml:description>Kjørefeltinndeling, 2 felt mot, 3 gjennomgående felt i fartsretning</gml:description>
			<gml:identifier codeSpace="https://github.com/tonoarmas/kodelister/blob/main/SkiltnummerOrdinærVi_10783.xml">21216</gml:identifier>
			<gml:name>538.23 - Kjørefeltinndeling, 2 felt mot, 3 gjennomgående felt i fartsretning</gml:name>
		</gml:Definition>
		<gml:Definition gml:id="18476">
			<gml:description>Kjørefeltendring med motgående.  (F.o.m. ver. 1.76: Skiltnummer endret fra "539.1")</gml:description>
			<gml:identifier codeSpace="https://github.com/tonoarmas/kodelister/blob/main/SkiltnummerOrdinærVi_10783.xml">18476</gml:identifier>
			<gml:name>539.01 - Kjørefeltendring med motgående</gml:name>
		</gml:Definition>
		<gml:Definition gml:id="18477">
			<gml:description>Kjørefeltendring med to felt.  (F.o.m. ver. 1.76: Skiltnummer endret fra "539.2")</gml:description>
			<gml:identifier codeSpace="https://github.com/tonoarmas/kodelister/blob/main/SkiltnummerOrdinærVi_10783.xml">18477</gml:identifier>
			<gml:name>539.02 - Kjørefeltendring med to felt</gml:name>
		</gml:Definition>
		<gml:Definition gml:id="17790">
			<gml:description>Opplysningstavle</gml:description>
			<gml:identifier codeSpace="https://github.com/tonoarmas/kodelister/blob/main/SkiltnummerOrdinærVi_10783.xml">17790</gml:identifier>
			<gml:name>560 - Opplysningstavle</gml:name>
		</gml:Definition>
		<gml:Definition gml:id="19071">
			<gml:description>Radiokanal</gml:description>
			<gml:identifier codeSpace="https://github.com/tonoarmas/kodelister/blob/main/SkiltnummerOrdinærVi_10783.xml">19071</gml:identifier>
			<gml:name>601 - Radiokanal</gml:name>
		</gml:Definition>
		<gml:Definition gml:id="17479">
			<gml:description>Tabellorienteringstavle for vanlig kryss.  (F.o.m. ver. 1.76: Skiltnummer endret fra "720.4")</gml:description>
			<gml:identifier codeSpace="https://github.com/tonoarmas/kodelister/blob/main/SkiltnummerOrdinærVi_10783.xml">17479</gml:identifier>
			<gml:name>701.1 - Tabellorienteringstavle for vanlig kryss</gml:name>
		</gml:Definition>
		<gml:Definition gml:id="17496">
			<gml:description>Tabellorienteringstavle for planskilt kryss på to- og trefeltsveg</gml:description>
			<gml:identifier codeSpace="https://github.com/tonoarmas/kodelister/blob/main/SkiltnummerOrdinærVi_10783.xml">17496</gml:identifier>
			<gml:name>701.2 - Tabellorienteringstavle for planskilt kryss på to- og trefeltsveg</gml:name>
		</gml:Definition>
		<gml:Definition gml:id="17480">
			<gml:description>Diagramorienteringstavle for rundkjøring.  (F.o.m. ver. 1.76: Skiltnummer endret fra "720.3")</gml:description>
			<gml:identifier codeSpace="https://github.com/tonoarmas/kodelister/blob/main/SkiltnummerOrdinærVi_10783.xml">17480</gml:identifier>
			<gml:name>703.1 - Diagramorienteringstavle for rundkjøring</gml:name>
		</gml:Definition>
		<gml:Definition gml:id="17497">
			<gml:description>Diagramorienteringstavle for kryss med spesiell utforming</gml:description>
			<gml:identifier codeSpace="https://github.com/tonoarmas/kodelister/blob/main/SkiltnummerOrdinærVi_10783.xml">17497</gml:identifier>
			<gml:name>703.2 - Diagramorienteringstavle for kryss med spesiell utforming</gml:name>
		</gml:Definition>
		<gml:Definition gml:id="17481">
			<gml:description>Avkjøringstavle. 1000-m tavle.  (F.o.m. ver. 1.76: Skiltnummer endret fra "720.1")</gml:description>
			<gml:identifier codeSpace="https://github.com/tonoarmas/kodelister/blob/main/SkiltnummerOrdinærVi_10783.xml">17481</gml:identifier>
			<gml:name>705.1 - Avkjøringstavle. 1000-m tavle</gml:name>
		</gml:Definition>
		<gml:Definition gml:id="17482">
			<gml:description>Avkjøringstavle. 500-m tavle.  (F.o.m. ver. 1.76: Skiltnummer endret fra "720.2")</gml:description>
			<gml:identifier codeSpace="https://github.com/tonoarmas/kodelister/blob/main/SkiltnummerOrdinærVi_10783.xml">17482</gml:identifier>
			<gml:name>705.2 - Avkjøringstavle. 500-m tavle</gml:name>
		</gml:Definition>
		<gml:Definition gml:id="17498">
			<gml:description>Kjørefeltorienteringstavle uten visningsmål</gml:description>
			<gml:identifier codeSpace="https://github.com/tonoarmas/kodelister/blob/main/SkiltnummerOrdinærVi_10783.xml">17498</gml:identifier>
			<gml:name>707.1 - Kjørefeltorienteringstavle uten visningsmål</gml:name>
		</gml:Definition>
		<gml:Definition gml:id="17499">
			<gml:description>Kjørefeltorienteringstavle med visningsmål</gml:description>
			<gml:identifier codeSpace="https://github.com/tonoarmas/kodelister/blob/main/SkiltnummerOrdinærVi_10783.xml">17499</gml:identifier>
			<gml:name>707.2 - Kjørefeltorienteringstavle med visningsmål</gml:name>
		</gml:Definition>
		<gml:Definition gml:id="17500">
			<gml:description>Kjørefeltorienteringstavle for feltsubtraksjon</gml:description>
			<gml:identifier codeSpace="https://github.com/tonoarmas/kodelister/blob/main/SkiltnummerOrdinærVi_10783.xml">17500</gml:identifier>
			<gml:name>707.3 - Kjørefeltorienteringstavle for feltsubtraksjon</gml:name>
		</gml:Definition>
		<gml:Definition gml:id="17501">
			<gml:description>Kjørefeltorienteringstavle for ferjeleie</gml:description>
			<gml:identifier codeSpace="https://github.com/tonoarmas/kodelister/blob/main/SkiltnummerOrdinærVi_10783.xml">17501</gml:identifier>
			<gml:name>707.4 - Kjørefeltorienteringstavle for ferjeleie</gml:name>
		</gml:Definition>
		<gml:Definition gml:id="17485">
			<gml:description>Portalorienteringstavle for ett kjørefelt.  (F.o.m. ver. 1.76: Skiltnummer endret fra "709")</gml:description>
			<gml:identifier codeSpace="https://github.com/tonoarmas/kodelister/blob/main/SkiltnummerOrdinærVi_10783.xml">17485</gml:identifier>
			<gml:name>709.1 - Portalorienteringstavle for ett kjørefelt</gml:name>
		</gml:Definition>
		<gml:Definition gml:id="17502">
			<gml:description>Portalorienteringstavle for flere kjørefelt</gml:description>
			<gml:identifier codeSpace="https://github.com/tonoarmas/kodelister/blob/main/SkiltnummerOrdinærVi_10783.xml">17502</gml:identifier>
			<gml:name>709.2 - Portalorienteringstavle for flere kjørefelt</gml:name>
		</gml:Definition>
		<gml:Definition gml:id="17503">
			<gml:description>Portalorienteringstavle for flere kjøreretninger</gml:description>
			<gml:identifier codeSpace="https://github.com/tonoarmas/kodelister/blob/main/SkiltnummerOrdinærVi_10783.xml">17503</gml:identifier>
			<gml:name>709.3 - Portalorienteringstavle for flere kjøreretninger</gml:name>
		</gml:Definition>
		<gml:Definition gml:id="17504">
			<gml:description>Portalorienteringstavle for feltsubtraksjon</gml:description>
			<gml:identifier codeSpace="https://github.com/tonoarmas/kodelister/blob/main/SkiltnummerOrdinærVi_10783.xml">17504</gml:identifier>
			<gml:name>709.4 - Portalorienteringstavle for feltsubtraksjon</gml:name>
		</gml:Definition>
		<gml:Definition gml:id="17487">
			<gml:description>Tabellvegviser, Rett fram.  (F.o.m. ver. 1.76: Skiltnummer endret fra "711")</gml:description>
			<gml:identifier codeSpace="https://github.com/tonoarmas/kodelister/blob/main/SkiltnummerOrdinærVi_10783.xml">17487</gml:identifier>
			<gml:name>711.R - Tabellvegviser, Rett fram</gml:name>
		</gml:Definition>
		<gml:Definition gml:id="17505">
			<gml:description>Tabellvegviser, Høyre, 90 grader</gml:description>
			<gml:identifier codeSpace="https://github.com/tonoarmas/kodelister/blob/main/SkiltnummerOrdinærVi_10783.xml">17505</gml:identifier>
			<gml:name>711.H90 - Tabellvegviser, Høyre, 90 grader</gml:name>
		</gml:Definition>
		<gml:Definition gml:id="17506">
			<gml:description>Tabellvegviser, Venstre, 90 grader</gml:description>
			<gml:identifier codeSpace="https://github.com/tonoarmas/kodelister/blob/main/SkiltnummerOrdinærVi_10783.xml">17506</gml:identifier>
			<gml:name>711.V90 - Tabellvegviser, Venstre, 90 grader</gml:name>
		</gml:Definition>
		<gml:Definition gml:id="17488">
			<gml:description>Vanlig vegviser, Venstre.  (F.o.m. ver. 1.76: Skiltnummer endret fra "713")</gml:description>
			<gml:identifier codeSpace="https://github.com/tonoarmas/kodelister/blob/main/SkiltnummerOrdinærVi_10783.xml">17488</gml:identifier>
			<gml:name>713.V - Vanlig vegviser, Venstre</gml:name>
		</gml:Definition>
		<gml:Definition gml:id="17507">
			<gml:description>Vanlig vegviser, Høyre</gml:description>
			<gml:identifier codeSpace="https://github.com/tonoarmas/kodelister/blob/main/SkiltnummerOrdinærVi_10783.xml">17507</gml:identifier>
			<gml:name>713.H - Vanlig vegviser, Høyre</gml:name>
		</gml:Definition>
		<gml:Definition gml:id="17489">
			<gml:description>Avkjøringsvegviser for veg uten kryssnummer.  (F.o.m. ver. 1.76: Skiltnummer endret fra "715")</gml:description>
			<gml:identifier codeSpace="https://github.com/tonoarmas/kodelister/blob/main/SkiltnummerOrdinærVi_10783.xml">17489</gml:identifier>
			<gml:name>715.1 - Avkjøringsvegviser for veg uten kryssnummer</gml:name>
		</gml:Definition>
		<gml:Definition gml:id="17508">
			<gml:description>Avkjøringsvegviser for veg med kryssnummer</gml:description>
			<gml:identifier codeSpace="https://github.com/tonoarmas/kodelister/blob/main/SkiltnummerOrdinærVi_10783.xml">17508</gml:identifier>
			<gml:name>715.2 - Avkjøringsvegviser for veg med kryssnummer</gml:name>
		</gml:Definition>
		<gml:Definition gml:id="17490">
			<gml:description>Kjørefeltvegviser</gml:description>
			<gml:identifier codeSpace="https://github.com/tonoarmas/kodelister/blob/main/SkiltnummerOrdinærVi_10783.xml">17490</gml:identifier>
			<gml:name>717 - Kjørefeltvegviser</gml:name>
		</gml:Definition>
		<gml:Definition gml:id="17491">
			<gml:description>Portalvegviser for ett kjørefelt.  (F.o.m. ver. 1.76: Skiltnummer endret fra "719")</gml:description>
			<gml:identifier codeSpace="https://github.com/tonoarmas/kodelister/blob/main/SkiltnummerOrdinærVi_10783.xml">17491</gml:identifier>
			<gml:name>719.1 - Portalvegviser for ett kjørefelt</gml:name>
		</gml:Definition>
		<gml:Definition gml:id="17509">
			<gml:description>Portalvegviser for flere kjørefelt</gml:description>
			<gml:identifier codeSpace="https://github.com/tonoarmas/kodelister/blob/main/SkiltnummerOrdinærVi_10783.xml">17509</gml:identifier>
			<gml:name>719.2 - Portalvegviser for flere kjørefelt</gml:name>
		</gml:Definition>
		<gml:Definition gml:id="17510">
			<gml:description>Portalvegviser for avkjøring</gml:description>
			<gml:identifier codeSpace="https://github.com/tonoarmas/kodelister/blob/main/SkiltnummerOrdinærVi_10783.xml">17510</gml:identifier>
			<gml:name>719.4 - Portalvegviser for avkjøring</gml:name>
		</gml:Definition>
		<gml:Definition gml:id="17511">
			<gml:description>Portalvegviser for ferjeleier og bomstasjoner</gml:description>
			<gml:identifier codeSpace="https://github.com/tonoarmas/kodelister/blob/main/SkiltnummerOrdinærVi_10783.xml">17511</gml:identifier>
			<gml:name>719.5 - Portalvegviser for ferjeleier og bomstasjoner</gml:name>
		</gml:Definition>
		<gml:Definition gml:id="21530">
			<gml:description>STOPP ved rødt blink Utrykning. (N303-krav 9.8)</gml:description>
			<gml:identifier codeSpace="https://github.com/tonoarmas/kodelister/blob/main/SkiltnummerOrdinærVi_10783.xml">21530</gml:identifier>
			<gml:name>808.611 - STOPP ved rødt blink Utrykning/Utrykking</gml:name>
		</gml:Definition>
		<gml:Definition gml:id="21531">
			<gml:description>STOPP ved rødt blink Bruåpning. (N303-krav 9.8)</gml:description>
			<gml:identifier codeSpace="https://github.com/tonoarmas/kodelister/blob/main/SkiltnummerOrdinærVi_10783.xml">21531</gml:identifier>
			<gml:name>808.612 - STOPP ved rødt blink Bruåpning/Bruopning</gml:name>
		</gml:Definition>
		<gml:Definition gml:id="21532">
			<gml:description>STOPP ved rødt blink Sterk vind. (N303-krav 9.8)</gml:description>
			<gml:identifier codeSpace="https://github.com/tonoarmas/kodelister/blob/main/SkiltnummerOrdinærVi_10783.xml">21532</gml:identifier>
			<gml:name>808.613 - STOPP ved rødt blink Sterk vind</gml:name>
		</gml:Definition>
		<gml:Definition gml:id="21533">
			<gml:description>STOPP ved rødt blink Flytrafikk. (N303-krav 9.8)</gml:description>
			<gml:identifier codeSpace="https://github.com/tonoarmas/kodelister/blob/main/SkiltnummerOrdinærVi_10783.xml">21533</gml:identifier>
			<gml:name>808.614 - STOPP ved rødt blink Flytrafikk</gml:name>
		</gml:Definition>
		<gml:Definition gml:id="21534">
			<gml:description>STOPP ved rødt blink Skredfare. (N303-krav 9.8)</gml:description>
			<gml:identifier codeSpace="https://github.com/tonoarmas/kodelister/blob/main/SkiltnummerOrdinærVi_10783.xml">21534</gml:identifier>
			<gml:name>808.615 - STOPP ved rødt blink Skredfare</gml:name>
		</gml:Definition>
		<gml:Definition gml:id="21535">
			<gml:description>STOPP ved rødt blink Flom. (N303-krav 9.8)</gml:description>
			<gml:identifier codeSpace="https://github.com/tonoarmas/kodelister/blob/main/SkiltnummerOrdinærVi_10783.xml">21535</gml:identifier>
			<gml:name>808.616 - STOPP ved rødt blink Flom/Flaum</gml:name>
		</gml:Definition>
		<gml:Definition gml:id="21536">
			<gml:description>STOPP ved rødt blink Høyt CO-nivå. (N303-krav 9.8)</gml:description>
			<gml:identifier codeSpace="https://github.com/tonoarmas/kodelister/blob/main/SkiltnummerOrdinærVi_10783.xml">21536</gml:identifier>
			<gml:name>808.617 - STOPP ved rødt blink Høyt/Høgt CO-nivå</gml:name>
		</gml:Definition>
		<gml:Definition gml:id="21537">
			<gml:description>STOPP ved rødt blink Ulykke. (N303-krav 9.8)</gml:description>
			<gml:identifier codeSpace="https://github.com/tonoarmas/kodelister/blob/main/SkiltnummerOrdinærVi_10783.xml">21537</gml:identifier>
			<gml:name>808.618 - STOPP ved rødt blink Ulykke/Ulukke</gml:name>
		</gml:Definition>
		<gml:Definition gml:id="21538">
			<gml:description>STOPP ved rødt blink Tunnel stengt. (N303-krav 9.8)</gml:description>
			<gml:identifier codeSpace="https://github.com/tonoarmas/kodelister/blob/main/SkiltnummerOrdinærVi_10783.xml">21538</gml:identifier>
			<gml:name>808.619 - STOPP ved rødt blink Tunnelen stengt/stengd</gml:name>
		</gml:Definition>
		<gml:Definition gml:id="21539">
			<gml:description>STOPP ved rødt blink Sporvogn. (N303-krav 9.8)</gml:description>
			<gml:identifier codeSpace="https://github.com/tonoarmas/kodelister/blob/main/SkiltnummerOrdinærVi_10783.xml">21539</gml:identifier>
			<gml:name>808.620 - STOPP ved rødt blink Sporvogn</gml:name>
		</gml:Definition>
		<gml:Definition gml:id="21540">
			<gml:description>STOPP ved rødt blink Buss. (N303-krav 9.8)</gml:description>
			<gml:identifier codeSpace="https://github.com/tonoarmas/kodelister/blob/main/SkiltnummerOrdinærVi_10783.xml">21540</gml:identifier>
			<gml:name>808.621 - STOPP ved rødt blink Buss</gml:name>
		</gml:Definition>
		<gml:Definition gml:id="21541">
			<gml:description>STOPP ved rødt blink Kryssende/Kryssande trafikk. (N303-krav 9.8)</gml:description>
			<gml:identifier codeSpace="https://github.com/tonoarmas/kodelister/blob/main/SkiltnummerOrdinærVi_10783.xml">21541</gml:identifier>
			<gml:name>808.622 - STOPP ved rødt blink Kryssende/Kryssande trafikk</gml:name>
		</gml:Definition>
		<gml:Definition gml:id="21542">
			<gml:description>STOPP ved rødt blink Vegen stengt/stengd. (N303-krav 9.8)</gml:description>
			<gml:identifier codeSpace="https://github.com/tonoarmas/kodelister/blob/main/SkiltnummerOrdinærVi_10783.xml">21542</gml:identifier>
			<gml:name>808.623 - STOPP ved rødt blink Vegen stengt/stengd</gml:name>
		</gml:Definition>
		<gml:Definition gml:id="17492">
			<gml:description>Retningsmarkering, Mot høyre</gml:description>
			<gml:identifier codeSpace="https://github.com/tonoarmas/kodelister/blob/main/SkiltnummerOrdinærVi_10783.xml">17492</gml:identifier>
			<gml:name>904H - Retningsmarkering, Mot høyre</gml:name>
		</gml:Definition>
		<gml:Definition gml:id="17483">
			<gml:description>Retningsmarkering, Mot venstre</gml:description>
			<gml:identifier codeSpace="https://github.com/tonoarmas/kodelister/blob/main/SkiltnummerOrdinærVi_10783.xml">17483</gml:identifier>
			<gml:name>904V - Retningsmarkering, Mot venstre</gml:name>
		</gml:Definition>
		<gml:Definition gml:id="17484">
			<gml:description>Avkjøringsmarkering</gml:description>
			<gml:identifier codeSpace="https://github.com/tonoarmas/kodelister/blob/main/SkiltnummerOrdinærVi_10783.xml">17484</gml:identifier>
			<gml:name>912 - Avkjøringsmarkering</gml:name>
		</gml:Definition>
	</gml:dictionaryEntry>
</gml:Dictionary>
