<?xml version="1.0" encoding="UTF-8"?>
<gml:Dictionary xmlns:gml="http://www.opengis.net/gml/3.2" xmlns:xsi="http://www.w3.org/2001/XMLSchema-instance" xsi:schemaLocation="http://www.opengis.net/gml/3.2 http://schemas.opengis.net/gml/3.2.1/gml.xsd" gml:id="kodelister.1924">
	<gml:description>Angir hvordan rørene er sammenkoplet.</gml:description>
	<gml:identifier codeSpace="https://github.com/tonoarmas/kodelister/blob/main/Skjøtemetode_1924.xml">Skjøtemetode_1924</gml:identifier>
	<gml:dictionaryEntry>
		<gml:Definition gml:id="2909">
			<gml:description></gml:description>
			<gml:identifier codeSpace="https://github.com/tonoarmas/kodelister/blob/main/Skjøtemetode_1924.xml">2909</gml:identifier>
			<gml:name>Helstøpt</gml:name>
		</gml:Definition>
		<gml:Definition gml:id="2910">
			<gml:description></gml:description>
			<gml:identifier codeSpace="https://github.com/tonoarmas/kodelister/blob/main/Skjøtemetode_1924.xml">2910</gml:identifier>
			<gml:name>Sveist</gml:name>
		</gml:Definition>
		<gml:Definition gml:id="2911">
			<gml:description></gml:description>
			<gml:identifier codeSpace="https://github.com/tonoarmas/kodelister/blob/main/Skjøtemetode_1924.xml">2911</gml:identifier>
			<gml:name>Muffe med pakning</gml:name>
		</gml:Definition>
		<gml:Definition gml:id="2912">
			<gml:description></gml:description>
			<gml:identifier codeSpace="https://github.com/tonoarmas/kodelister/blob/main/Skjøtemetode_1924.xml">2912</gml:identifier>
			<gml:name>Muffe uten pakning</gml:name>
		</gml:Definition>
		<gml:Definition gml:id="2913">
			<gml:description></gml:description>
			<gml:identifier codeSpace="https://github.com/tonoarmas/kodelister/blob/main/Skjøtemetode_1924.xml">2913</gml:identifier>
			<gml:name>Fals</gml:name>
		</gml:Definition>
		<gml:Definition gml:id="2914">
			<gml:description></gml:description>
			<gml:identifier codeSpace="https://github.com/tonoarmas/kodelister/blob/main/Skjøtemetode_1924.xml">2914</gml:identifier>
			<gml:name>Flens</gml:name>
		</gml:Definition>
		<gml:Definition gml:id="2915">
			<gml:description></gml:description>
			<gml:identifier codeSpace="https://github.com/tonoarmas/kodelister/blob/main/Skjøtemetode_1924.xml">2915</gml:identifier>
			<gml:name>Butt i butt</gml:name>
		</gml:Definition>
		<gml:Definition gml:id="3942">
			<gml:description></gml:description>
			<gml:identifier codeSpace="https://github.com/tonoarmas/kodelister/blob/main/Skjøtemetode_1924.xml">3942</gml:identifier>
			<gml:name>Krympeplast</gml:name>
		</gml:Definition>
	</gml:dictionaryEntry>
</gml:Dictionary>
