<?xml version="1.0" encoding="UTF-8"?>
<gml:Dictionary xmlns:gml="http://www.opengis.net/gml/3.2" xmlns:xsi="http://www.w3.org/2001/XMLSchema-instance" xsi:schemaLocation="http://www.opengis.net/gml/3.2 http://schemas.opengis.net/gml/3.2.1/gml.xsd" gml:id="kodelister.4645">
	<gml:description>Relatert til sikkerhetsutstyr i HB N500 (021)</gml:description>
	<gml:identifier codeSpace="https://github.com/tonoarmas/kodelister/blob/main/StandardSikkerhetsuts_4645.xml">StandardSikkerhetsuts_4645</gml:identifier>
	<gml:dictionaryEntry>
		<gml:Definition gml:id="5598">
			<gml:description></gml:description>
			<gml:identifier codeSpace="https://github.com/tonoarmas/kodelister/blob/main/StandardSikkerhetsuts_4645.xml">5598</gml:identifier>
			<gml:name>Ja</gml:name>
		</gml:Definition>
		<gml:Definition gml:id="5615">
			<gml:description></gml:description>
			<gml:identifier codeSpace="https://github.com/tonoarmas/kodelister/blob/main/StandardSikkerhetsuts_4645.xml">5615</gml:identifier>
			<gml:name>Brukbar</gml:name>
		</gml:Definition>
		<gml:Definition gml:id="5632">
			<gml:description></gml:description>
			<gml:identifier codeSpace="https://github.com/tonoarmas/kodelister/blob/main/StandardSikkerhetsuts_4645.xml">5632</gml:identifier>
			<gml:name>Nei</gml:name>
		</gml:Definition>
	</gml:dictionaryEntry>
</gml:Dictionary>
