<?xml version="1.0" encoding="UTF-8"?>
<gml:Dictionary xmlns:gml="http://www.opengis.net/gml/3.2" xmlns:xsi="http://www.w3.org/2001/XMLSchema-instance" xsi:schemaLocation="http://www.opengis.net/gml/3.2 http://schemas.opengis.net/gml/3.2.1/gml.xsd" gml:id="kodelister.11386">
	<gml:description>Angir hva slags type vertikaldren som er installert.</gml:description>
	<gml:identifier codeSpace="https://github.com/tonoarmas/kodelister/blob/main/Type_11386.xml">Type_11386</gml:identifier>
	<gml:dictionaryEntry>
		<gml:Definition gml:id="19228">
			<gml:description></gml:description>
			<gml:identifier codeSpace="https://github.com/tonoarmas/kodelister/blob/main/Type_11386.xml">19228</gml:identifier>
			<gml:name>Sand/grus</gml:name>
		</gml:Definition>
	</gml:dictionaryEntry>
</gml:Dictionary>
